earningscall/__init__.py
earningscall/api.py
earningscall/calendar.py
earningscall/company.py
earningscall/errors.py
earningscall/event.py
earningscall/exchanges.py
earningscall/exports.py
earningscall/sectors.py
earningscall/symbols.py
earningscall/transcript.py
earningscall/utils.py
earningscall-1.4.0.dist-info/METADATA
earningscall-1.4.0.dist-info/WHEEL
earningscall-1.4.0.dist-info/licenses/LICENSE
earningscall-1.4.0.dist-info/RECORD
