Metadata-Version: 2.4
Name: earningscall
Version: 1.4.0
Summary: The EarningsCall Python library provides convenient access to the EarningsCall API.  It includes a pre-defined set of classes for API resources that initialize themselves dynamically from API responses.
Project-URL: Homepage, https://earningscall.biz
Project-URL: Documentation, https://github.com/EarningsCall/earningscall-python
Project-URL: Repository, https://github.com/EarningsCall/earningscall-python
Project-URL: Issues, https://github.com/EarningsCall/earningscall-python/issues
Project-URL: Source, https://github.com/EarningsCall/earningscall-python
Project-URL: Changelog, https://github.com/EarningsCall/earningscall-python/blob/master/CHANGELOG.md
Author-email: EarningsCall <dev@earningscall.biz>
License: MIT License
License-File: LICENSE
Keywords: earning call app,earnings call,earnings call api,earnings call app,earnings call transcript api,earnings call transcripts,earnings call transcripts api,earnings calls,earnings transcript api,listen to earnings calls,transcripts,where to listen to earnings calls
Classifier: Development Status :: 5 - Production/Stable
Classifier: Intended Audience :: Developers
Classifier: License :: OSI Approved :: MIT License
Classifier: Programming Language :: Python :: 3
Classifier: Programming Language :: Python :: 3.8
Classifier: Programming Language :: Python :: 3.9
Classifier: Programming Language :: Python :: 3.10
Classifier: Programming Language :: Python :: 3.11
Classifier: Programming Language :: Python :: 3.12
Classifier: Programming Language :: Python :: 3.13
Classifier: Topic :: Software Development :: Libraries :: Python Modules
Classifier: Typing :: Typed
Requires-Python: >=3.8
Requires-Dist: dataclasses-json>=0.6.4
Requires-Dist: requests-cache>=1.2.0
Requires-Dist: requests>=2.30.0
